charprinto/LICENSE
charprinto/README.md
charprinto/pyproject.toml
charprinto/setup.py
charprinto/charprinto/__init__.py
charprinto/tests/__init__.py
charprinto/tests/test_charprinto.py
charprinto-2.0.1.dist-info/METADATA
charprinto-2.0.1.dist-info/WHEEL
charprinto-2.0.1.dist-info/entry_points.txt
charprinto-2.0.1.dist-info/top_level.txt
charprinto-2.0.1.dist-info/RECORD
