Metadata-Version: 2.1
Name: charprinto
Version: 2.0.1
Summary: Print strings character by character easily
Home-page: UNKNOWN
Author: AverseABFun
Author-email: averse.abfun@gmail.com
License: MIT
Platform: UNKNOWN
Classifier: License :: OSI Approved :: MIT License
Classifier: Programming Language :: Python :: 3
Classifier: Programming Language :: Python :: 3.7
Requires-Dist: termcolor
Requires-Dist: cursor
Requires-Dist: sys
Requires-Dist: os
